Builds.txt
License.txt
MANIFEST.in
README.rst
setup.py
dAmnViper/__init__.py
dAmnViper/base.py
dAmnViper/data.py
dAmnViper/net.py
dAmnViper/parse.py
dAmnViper.egg-info/PKG-INFO
dAmnViper.egg-info/SOURCES.txt
dAmnViper.egg-info/dependency_links.txt
dAmnViper.egg-info/requires.txt
dAmnViper.egg-info/top_level.txt
dAmnViper/dA/__init__.py
dAmnViper/dA/api.py
dAmnViper/dA/oauth.py
dAmnViper/examples/__init__.py
dAmnViper/examples/bare.py
dAmnViper/examples/bot.py
dAmnViper/examples/da_api.py
dAmnViper/examples/oauth.py
dAmnViper/examples/util.py
dAmnViper/test/__init__.py
dAmnViper/test/test_auth_client.py
dAmnViper/test/test_auth_resource.py
dAmnViper/test/test_client_connection.py
dAmnViper/test/test_dapi_client.py
dAmnViper/test/test_dapi_receiver.py
dAmnViper/test/test_dapi_request.py
dAmnViper/test/test_packet_event_object.py
dAmnViper/test/test_packet_object.py
dAmnViper/test/test_protocol_parser.py
dAmnViper/test/dummy/__init__.py
dAmnViper/test/dummy/client.py
dAmnViper/test/dummy/dapi.py
dAmnViper/test/dummy/oauth.py
dAmnViper/test/dummy/server.py