Metadata-Version: 1.1
Name: dAmnViper
Version: 3.59
Summary: dAmn connection library
Home-page: https://github.com/photofroggy/dAmnViper
Author: photofroggy
Author-email: froggywillneverdie@msn.com
License: UNKNOWN
Platform: Any
Classifier: Natural Language :: English
Classifier: Development Status :: 4 - Beta
Classifier: Intended Audience :: Developers
Classifier: Operating System :: OS Independent
Classifier: Programming Language :: Python :: 2
Classifier: Programming Language :: Python :: 2.7
Classifier: Topic :: Internet :: WWW/HTTP :: Dynamic Content
Classifier: License :: OSI Approved :: ISC License (ISCL)
Classifier: Topic :: Software Development :: Libraries :: Application Frameworks
Requires: twisted (>=11.0.0)
Provides: dAmnViper
